feno/__init__.py
feno/__main__.py
feno/actions.py
feno/cases.py
feno/collect.py
feno/debug.py
feno/decoder.py
feno/filter.py
feno/html.py
feno/indexer.py
feno/jsontools.py
feno/log.py
feno/mdpp.py
feno/older.py
feno/remote_md.py
feno/text.py
feno/title.py
feno-0.6.2.dist-info/LICENSE
feno-0.6.2.dist-info/METADATA
feno-0.6.2.dist-info/WHEEL
feno-0.6.2.dist-info/entry_points.txt
feno-0.6.2.dist-info/top_level.txt
feno-0.6.2.dist-info/RECORD
