Metadata-Version: 2.1
Name: feno
Version: 0.6.2
Summary: feno: Flexible Exercise Notation Organizer
Home-page: https://github.com/senapk/feno
Author: David Sena Oliveira
Author-email: sena@ufc.br
Project-URL: Bug Reports, https://github.com/senapk/feno/issues
Project-URL: Source, https://github.com/senapk/feno/
Keywords: programming,learning
Classifier: Development Status :: 3 - Alpha
Classifier: Operating System :: OS Independent
Classifier: Topic :: Education
Classifier: License :: OSI Approved :: GNU General Public License v3 (GPLv3)
Classifier: Programming Language :: Python :: 3.8
Requires-Python: >=3.7, <4
License-File: LICENSE
Requires-Dist: build
Requires-Dist: twine
Requires-Dist: chardet
Requires-Dist: markdown
Requires-Dist: pyyaml
Provides-Extra: dev
Requires-Dist: check-manifest; extra == "dev"
Provides-Extra: test
Requires-Dist: coverage; extra == "test"
